companyClassifier/__init__.py
companyClassifier/companyClassifier.py
companyClassifier/models/__init__.py
companyClassifier/models/config.json
companyClassifier/models/tokenizer.joblib
companyClassifier-3.0.2.dist-info/LICENSE
companyClassifier-3.0.2.dist-info/METADATA
companyClassifier-3.0.2.dist-info/WHEEL
companyClassifier-3.0.2.dist-info/top_level.txt
companyClassifier-3.0.2.dist-info/RECORD
