Metadata-Version: 2.1
Name: companyClassifier
Version: 3.0.2
Summary: UNKNOWN
Home-page: UNKNOWN
License: UNKNOWN
Platform: UNKNOWN
License-File: LICENSE
Requires-Dist: wget
Requires-Dist: keras (>=2.6.0)
Requires-Dist: tqdm
Requires-Dist: joblib
Requires-Dist: transformers (>=4.11.3)
Requires-Dist: numpy (>=1.13.3)
Requires-Dist: tensorflow (>=2.6.0)
